quantization.cp37-win_amd64.pyd
memtorch/__init__.py
memtorch/utils.py
memtorch/version.py
memtorch/bh/Quantize.py
memtorch/bh/StochasticParameter.py
memtorch/bh/__init__.py
memtorch/bh/crossbar/Crossbar.py
memtorch/bh/crossbar/Program.py
memtorch/bh/crossbar/Tile.py
memtorch/bh/crossbar/__init__.py
memtorch/bh/memristor/Data_Driven.py
memtorch/bh/memristor/LinearIonDrift.py
memtorch/bh/memristor/Memristor.py
memtorch/bh/memristor/Stanford_PKU.py
memtorch/bh/memristor/VTEAM.py
memtorch/bh/memristor/__init__.py
memtorch/bh/memristor/window/Biolek.py
memtorch/bh/memristor/window/Jogelkar.py
memtorch/bh/memristor/window/Prodromakis.py
memtorch/bh/memristor/window/__init__.py
memtorch/bh/nonideality/DeviceFaults.py
memtorch/bh/nonideality/Endurance.py
memtorch/bh/nonideality/FiniteConductanceStates.py
memtorch/bh/nonideality/NonIdeality.py
memtorch/bh/nonideality/NonLinear.py
memtorch/bh/nonideality/Retention.py
memtorch/bh/nonideality/__init__.py
memtorch/bh/nonideality/endurance_retention_models/__init__.py
memtorch/bh/nonideality/endurance_retention_models/conductance_drift.py
memtorch/bh/nonideality/endurance_retention_models/empirical_metal_oxide_RRAM.py
memtorch/map/Module.py
memtorch/map/Parameter.py
memtorch/map/__init__.py
memtorch/mn/Conv1d.py
memtorch/mn/Conv2d.py
memtorch/mn/Conv3d.py
memtorch/mn/Linear.py
memtorch/mn/Module.py
memtorch/mn/__init__.py
memtorch/submodules/__init__.py
memtorch/submodules/pytorch-playground/__init__.py
memtorch/submodules/pytorch-playground/quantize.py
memtorch/submodules/pytorch-playground/setup.py
memtorch/submodules/pytorch-playground/cifar/__init__.py
memtorch/submodules/pytorch-playground/cifar/dataset.py
memtorch/submodules/pytorch-playground/cifar/model.py
memtorch/submodules/pytorch-playground/cifar/train.py
memtorch/submodules/pytorch-playground/imagenet/__init__.py
memtorch/submodules/pytorch-playground/imagenet/alexnet.py
memtorch/submodules/pytorch-playground/imagenet/dataset.py
memtorch_cpu-1.1.1.dist-info/LICENSE
memtorch_cpu-1.1.1.dist-info/METADATA
memtorch_cpu-1.1.1.dist-info/WHEEL
memtorch_cpu-1.1.1.dist-info/top_level.txt
memtorch_cpu-1.1.1.dist-info/RECORD
